gtAI/CA_RSCU.py
gtAI/ENc.py
gtAI/Run_gtAI.py
gtAI/__init__.py
gtAI/bygaft.py
gtAI/gtAI.py
gtAI/new_flow.py
gtAI-1.0.6.dist-info/METADATA
gtAI-1.0.6.dist-info/WHEEL
gtAI-1.0.6.dist-info/top_level.txt
gtAI-1.0.6.dist-info/RECORD
