Metadata-Version: 2.1
Name: gtAI
Version: 1.0.6
Summary: To estimate the tRNA adaptation index (tAI)
Home-page: https://github.com/AliYoussef96/gtAI
Author: Ali Mostafa Anwar
Author-email: aliali.mostafa99@gmail.com
License: GPLv3
Classifier: License :: OSI Approved :: GNU General Public License v3 (GPLv3)
Classifier: Programming Language :: Python :: 3
Classifier: Intended Audience :: Science/Research
Classifier: Topic :: Scientific/Engineering :: Bio-Informatics
Requires-Python: >=3.7.0
Requires-Dist: biopython
Requires-Dist: pandas
Requires-Dist: numpy
Requires-Dist: gaft
Requires-Dist: lxml
